tap_getpocket/__init__.py
tap_getpocket/auth.py
tap_getpocket/client.py
tap_getpocket/streams.py
tap_getpocket/tap.py
tap_getpocket/tests/__init__.py
tap_getpocket/tests/test_core.py
tap_getpocket/ttt.py
tap_getpocket-1.1.0.dist-info/entry_points.txt
tap_getpocket-1.1.0.dist-info/WHEEL
tap_getpocket-1.1.0.dist-info/METADATA
tap_getpocket-1.1.0.dist-info/RECORD
