Metadata-Version: 2.1
Name: tap-getpocket
Version: 1.1.0
Summary: `tap-getpocket` is a Singer tap for GetPocket, built with the Meltano SDK for Singer Taps.
License: Apache 2.0
Keywords: ELT,GetPocket
Author: Elena Velte
Requires-Python: >=3.6.2,<3.10
Classifier: License :: Other/Proprietary License
Classifier: Programming Language :: Python :: 3
Classifier: Programming Language :: Python :: 3.7
Classifier: Programming Language :: Python :: 3.8
Classifier: Programming Language :: Python :: 3.9
Requires-Dist: requests (>=2.25.1,<3.0.0)
Requires-Dist: singer-sdk (>=0.3.13,<0.4.0)
